Etapa_2-Projeto_da_ULA/Arithmetic_Logic_Unit/alu.vhdl
-- File: alu.vhdl
LIBRARY ieee;
USE ieee.std_logic_1164.ALL;

ENTITY alu IS
    PORT (
        A        : IN  STD_LOGIC;
        B        : IN  STD_LOGIC;
        CarryIn  : IN  STD_LOGIC;
        Operacao : IN  STD_LOGIC_VECTOR(1 DOWNTO 0);
        Resultado: OUT STD_LOGIC;
        CarryOut : OUT STD_LOGIC
    );
END ENTITY alu;

ARCHITECTURE behavioral OF alu IS
BEGIN
    PROCESS (A, B, CarryIn, Operacao)
    BEGIN
        CASE Operacao IS
            WHEN "00" => -- AND
                Resultado <= A AND B;
                CarryOut  <= '0';
            WHEN "01" => -- ADD
                Resultado <= A XOR B XOR CarryIn;
                CarryOut  <= (A AND B) OR (CarryIn AND (A XOR B));
            WHEN "10" => -- SUB
                Resultado <= A XOR (NOT B) XOR CarryIn;
                CarryOut  <= (A AND (NOT B)) OR (CarryIn AND (A XOR (NOT B)));
            WHEN "11" => -- OR
                Resultado <= A OR B;
                CarryOut  <= '0';
            WHEN OTHERS =>
                Resultado <= 'X';
                CarryOut  <= 'X';
        END CASE;
    END PROCESS;
END ARCHITECTURE behavioral;

Etapa_2-Projeto_da_ULA/Arithmetic_Logic_Unit/alu_tb_1bit.vhdl
-- File: alu_tb_1bit.vhdl
-- Description: Testbench para a ULA de 1 bit (CORRIGIDO).

LIBRARY ieee;
USE ieee.std_logic_1164.ALL;

ENTITY alu_tb_1bit IS
END ENTITY alu_tb_1bit;

ARCHITECTURE test OF alu_tb_1bit IS
    COMPONENT alu IS
        PORT (
            A        : IN  STD_LOGIC;
            B        : IN  STD_LOGIC;
            CarryIn  : IN  STD_LOGIC;
            Operacao : IN  STD_LOGIC_VECTOR(1 DOWNTO 0);
            Resultado: OUT STD_LOGIC;
            CarryOut : OUT STD_LOGIC
        );
    END COMPONENT;

    SIGNAL s_A, s_B, s_CarryIn, s_Resultado, s_CarryOut: STD_LOGIC;
    SIGNAL s_Operacao: STD_LOGIC_VECTOR(1 DOWNTO 0);
BEGIN
    -- CORREÇÃO: Usando associação por nome para conectar as portas.
    uut: alu PORT MAP(
        A         => s_A,
        B         => s_B,
        CarryIn   => s_CarryIn,
        Operacao  => s_Operacao,
        Resultado => s_Resultado,
        CarryOut  => s_CarryOut
    );

    stim_proc: PROCESS
    BEGIN
        -- Testes para a operação ADD ("01")
        -- Teste 0+0+0: Res=0, Cout=0
        s_Operacao <= "01"; s_A <= '0'; s_B <= '0'; s_CarryIn <= '0'; WAIT FOR 10 ns;
        -- Teste 0+0+1: Res=1, Cout=0
        s_Operacao <= "01"; s_A <= '0'; s_B <= '0'; s_CarryIn <= '1'; WAIT FOR 10 ns;
        -- Teste 0+1+0: Res=1, Cout=0
        s_Operacao <= "01"; s_A <= '0'; s_B <= '1'; s_CarryIn <= '0'; WAIT FOR 10 ns;
        -- Teste 0+1+1: Res=0, Cout=1
        s_Operacao <= "01"; s_A <= '0'; s_B <= '1'; s_CarryIn <= '1'; WAIT FOR 10 ns;
        -- Teste 1+0+0: Res=1, Cout=0
        s_Operacao <= "01"; s_A <= '1'; s_B <= '0'; s_CarryIn <= '0'; WAIT FOR 10 ns;
        -- Teste 1+0+1: Res=0, Cout=1
        s_Operacao <= "01"; s_A <= '1'; s_B <= '0'; s_CarryIn <= '1'; WAIT FOR 10 ns;
        -- Teste 1+1+0: Res=0, Cout=1
        s_Operacao <= "01"; s_A <= '1'; s_B <= '1'; s_CarryIn <= '0'; WAIT FOR 10 ns;
        -- Teste 1+1+1: Res=1, Cout=1
        s_Operacao <= "01"; s_A <= '1'; s_B <= '1'; s_CarryIn <= '1'; WAIT FOR 10 ns;
        -- Testes para a operação SUB ("10")
        -- Teste 0-0 (com Cin=0): Res=1, Cout=0 (com empréstimo)
        s_Operacao <= "10"; s_A <= '0'; s_B <= '0'; s_CarryIn <= '0'; WAIT FOR 10 ns;
        -- Teste 0-0 (com Cin=1): Res=0, Cout=1 (sem empréstimo)
        s_Operacao <= "10"; s_A <= '0'; s_B <= '0'; s_CarryIn <= '1'; WAIT FOR 10 ns;
        -- Teste 0-1 (com Cin=0): Res=0, Cout=0 (com empréstimo)
        s_Operacao <= "10"; s_A <= '0'; s_B <= '1'; s_CarryIn <= '0'; WAIT FOR 10 ns;
        -- Teste 0-1 (com Cin=1): Res=1, Cout=0 (com empréstimo)
        s_Operacao <= "10"; s_A <= '0'; s_B <= '1'; s_CarryIn <= '1'; WAIT FOR 10 ns;
        -- Teste 1-0 (com Cin=0): Res=0, Cout=1 (sem empréstimo)
        s_Operacao <= "10"; s_A <= '1'; s_B <= '0'; s_CarryIn <= '0'; WAIT FOR 10 ns;
        -- Teste 1-0 (com Cin=1): Res=1, Cout=1 (sem empréstimo)
        s_Operacao <= "10"; s_A <= '1'; s_B <= '0'; s_CarryIn <= '1'; WAIT FOR 10 ns;
        -- Teste 1-1 (com Cin=0): Res=1, Cout=0 (com empréstimo)
        s_Operacao <= "10"; s_A <= '1'; s_B <= '1'; s_CarryIn <= '0'; WAIT FOR 10 ns;
        -- Teste 1-1 (com Cin=1): Res=0, Cout=1 (sem empréstimo)
        s_Operacao <= "10"; s_A <= '1'; s_B <= '1'; s_CarryIn <= '1'; WAIT FOR 10 ns;
        -- Teste AND: 1 AND 0 = 0
        s_Operacao <= "00"; s_A <= '1'; s_B <= '0'; s_CarryIn <= '0'; WAIT FOR 10 ns;
        -- Teste AND: 0 AND 1 = 0
        s_Operacao <= "00"; s_A <= '0'; s_B <= '1'; s_CarryIn <= '0'; WAIT FOR 10 ns;
        -- Adicione este teste para ver o resultado 1 na operação AND
        s_Operacao <= "00"; s_A <= '1'; s_B <= '1'; s_CarryIn <= '0'; WAIT FOR 10 ns;
        -- Teste AND: 0 AND 0 = 0
        s_Operacao <= "00"; s_A <= '0'; s_B <= '0'; s_CarryIn <= '0'; WAIT FOR 10 ns;
        -- Teste OR: 1 OR 0 = 1
        s_Operacao <= "11"; s_A <= '1'; s_B <= '0'; s_CarryIn <= '0'; WAIT FOR 10 ns;
        -- Teste OR: 0 OR 1 = 1
        s_Operacao <= "11"; s_A <= '0'; s_B <= '1'; s_CarryIn <= '0'; WAIT FOR 10 ns;
        -- Teste OR: 1 OR 1 = 1
        s_Operacao <= "11"; s_A <= '1'; s_B <= '1'; s_CarryIn <= '0'; WAIT FOR 10 ns;
        -- Teste OR: 0 OR 0 = 0
        s_Operacao <= "11"; s_A <= '0'; s_B <= '0'; s_CarryIn <= '0'; WAIT FOR 10 ns;
        WAIT;
    END PROCESS;
END ARCHITECTURE test;

Etapa_2-Projeto_da_ULA/Arithmetic_Logic_Unit/wave_1bit.vcd
$date
  Thu Jun 12 12:25:22 2025
$end
$version
  GHDL v0
$end
$timescale
  1 fs
$end
$scope module standard $end
$upscope $end
$scope module std_logic_1164 $end
$upscope $end
$scope module alu_tb_1bit $end
$var reg 1 ! s_a $end
$var reg 1 " s_b $end
$var reg 1 # s_carryin $end
$var reg 1 $ s_resultado $end
$var reg 1 % s_carryout $end
$var reg 2 & s_operacao[1:0] $end
$scope module uut $end
$var reg 1 ' a $end
$var reg 1 ( b $end
$var reg 1 ) carryin $end
$var reg 2 * operacao[1:0] $end
$var reg 1 + resultado $end
$var reg 1 , carryout $end
$upscope $end
$upscope $end
$enddefinitions $end
#0
0!
0"
0#
0$
0%
b01 &
0'
0(
0)
b01 *
0+
0,
#10000000
1#
1$
1)
1+
#20000000
1"
0#
1(
0)
#30000000
1#
0$
1%
1)
0+
1,
#40000000
1!
0"
0#
1$
0%
1'
0(
0)
1+
0,
#50000000
1#
0$
1%
1)
0+
1,
#60000000
1"
0#
1(
0)
#70000000
1#
1$
1)
1+
#80000000
0!
0"
0#
0%
b10 &
0'
0(
0)
b10 *
0,
#90000000
1#
0$
1%
1)
0+
1,
#100000000
1"
0#
0%
1(
0)
0,
#110000000
1#
1$
1)
1+
#120000000
1!
0"
0#
0$
1%
1'
0(
0)
0+
1,
#130000000
1#
1$
1)
1+
#140000000
1"
0#
0%
1(
0)
0,
#150000000
1#
0$
1%
1)
0+
1,
#160000000
0"
0#
0%
b00 &
0(
0)
b00 *
0,
#170000000
0!
1"
0'
1(
#180000000
1!
1$
1'
1+
#190000000
0!
0"
0$
0'
0(
0+
#200000000
1!
1$
b11 &
1'
b11 *
1+
#210000000
0!
1"
0'
1(
#220000000
1!
1'
#230000000
0!
0"
0$
0'
0(
0+
